quickhttp/__init__.py
quickhttp/__main__.py
quickhttp/cli.py
quickhttp/exceptions.py
quickhttp/http_server.py
quickhttp-2.1.0.dist-info/METADATA
quickhttp-2.1.0.dist-info/WHEEL
quickhttp-2.1.0.dist-info/entry_points.txt
quickhttp-2.1.0.dist-info/licenses/LICENSE
quickhttp-2.1.0.dist-info/RECORD
