Metadata-Version: 2.4
Name: quickhttp
Version: 2.1.0
Summary: Lightweight CLI that wraps Python's http.server with automatic port-finding and shutdown.
Project-URL: homepage, https://github.com/jayqi/quickhttp
Project-URL: repository, https://github.com/jayqi/quickhttp
Project-URL: documentation, https://jayqi.github.io/quickhttp/
Author-email: Jay Qi <jayqi.opensource@gmail.com>
License-Expression: MIT
License-File: LICENSE
Keywords: dev server,http server
Classifier: Intended Audience :: Developers
Classifier: Operating System :: OS Independent
Classifier: Topic :: Internet :: WWW/HTTP :: HTTP Servers
Requires-Python: >=3.8
Requires-Dist: pytimeparse>=1.1.8
Requires-Dist: typer>=0.3.0
